[
{
  "directory": "c:\\Users\\angre\\Documents\\VSCode\\source\\birdseye",
  "arguments": ["C:\\Program Files (x86)\\Microsoft Visual Studio\\2022\\BuildTools\\VC\\Tools\\MSVC\\14.42.34433\\bin\\HostX64\\x64\\cl.exe", "/c", "/nologo", "/W3", "/O1", "/GL", "/std:c++20", "/Iinclude", "/DSPDLOG_ACTIVE_LEVEL=SPDLOG_LEVEL_TRACE", "/DCURL_STATICLIB", "/EHsc", "/IC:\\Users\\angre\\AppData\\Local\\.xmake\\packages\\s\\spdlog\\v1.15.0\\b90f1a53d8774e77a175f0acf6ca3954\\include", "/IC:\\Users\\angre\\AppData\\Local\\.xmake\\packages\\s\\sqlitecpp\\3.3.2\\e6fbae8bcc0c4463860caf64d1463071\\include", "/IC:\\Users\\angre\\AppData\\Local\\.xmake\\packages\\l\\libcurl\\8.11.0\\018717789a0b4a8e9e3ea73514f790f5\\include", "/IC:\\Users\\angre\\AppData\\Local\\.xmake\\packages\\w\\wolfssl\\5.7.2\\ad2f2710804849fba36fe16b7687c73a\\include", "/IC:\\Users\\angre\\AppData\\Local\\.xmake\\packages\\n\\nlohmann_json\\v3.11.3\\826582eb66794908a16a49dbdd33bec4\\include", "/utf-8", "/DNDEBUG", "/Fobuild\\.objs\\birdseye\\windows\\x64\\release\\src\\database.cpp.obj", "src\\database.cpp", "-imsvc", "C:\\Program Files (x86)\\Windows Kits\\10\\Include\\10.0.22621.0\\cppwinrt", "-imsvc", "C:\\Program Files (x86)\\Windows Kits\\10\\Include\\10.0.22621.0\\shared", "-imsvc", "C:\\Program Files (x86)\\Windows Kits\\10\\Include\\10.0.22621.0\\ucrt", "-imsvc", "C:\\Program Files (x86)\\Windows Kits\\10\\Include\\10.0.22621.0\\um", "-imsvc", "C:\\Program Files (x86)\\Windows Kits\\10\\Include\\10.0.22621.0\\winrt", "-imsvc", "C:\\Program Files (x86)\\Microsoft Visual Studio\\2022\\BuildTools\\VC\\Tools\\MSVC\\14.42.34433\\include"],
  "file": "src\\database.cpp"
},
{
  "directory": "c:\\Users\\angre\\Documents\\VSCode\\source\\birdseye",
  "arguments": ["C:\\Program Files (x86)\\Microsoft Visual Studio\\2022\\BuildTools\\VC\\Tools\\MSVC\\14.42.34433\\bin\\HostX64\\x64\\cl.exe", "/c", "/nologo", "/W3", "/O1", "/GL", "/std:c++20", "/Iinclude", "/DSPDLOG_ACTIVE_LEVEL=SPDLOG_LEVEL_TRACE", "/DCURL_STATICLIB", "/EHsc", "/IC:\\Users\\angre\\AppData\\Local\\.xmake\\packages\\s\\spdlog\\v1.15.0\\b90f1a53d8774e77a175f0acf6ca3954\\include", "/IC:\\Users\\angre\\AppData\\Local\\.xmake\\packages\\s\\sqlitecpp\\3.3.2\\e6fbae8bcc0c4463860caf64d1463071\\include", "/IC:\\Users\\angre\\AppData\\Local\\.xmake\\packages\\l\\libcurl\\8.11.0\\018717789a0b4a8e9e3ea73514f790f5\\include", "/IC:\\Users\\angre\\AppData\\Local\\.xmake\\packages\\w\\wolfssl\\5.7.2\\ad2f2710804849fba36fe16b7687c73a\\include", "/IC:\\Users\\angre\\AppData\\Local\\.xmake\\packages\\n\\nlohmann_json\\v3.11.3\\826582eb66794908a16a49dbdd33bec4\\include", "/utf-8", "/DNDEBUG", "/Fobuild\\.objs\\birdseye\\windows\\x64\\release\\src\\main.cpp.obj", "src\\main.cpp", "-imsvc", "C:\\Program Files (x86)\\Windows Kits\\10\\Include\\10.0.22621.0\\cppwinrt", "-imsvc", "C:\\Program Files (x86)\\Windows Kits\\10\\Include\\10.0.22621.0\\shared", "-imsvc", "C:\\Program Files (x86)\\Windows Kits\\10\\Include\\10.0.22621.0\\ucrt", "-imsvc", "C:\\Program Files (x86)\\Windows Kits\\10\\Include\\10.0.22621.0\\um", "-imsvc", "C:\\Program Files (x86)\\Windows Kits\\10\\Include\\10.0.22621.0\\winrt", "-imsvc", "C:\\Program Files (x86)\\Microsoft Visual Studio\\2022\\BuildTools\\VC\\Tools\\MSVC\\14.42.34433\\include"],
  "file": "src\\main.cpp"
}]
